apybiomart/__init__.py
apybiomart/apybiomart.py
apybiomart/classes.py
apybiomart/cli.py
apybiomart-0.5.3.dist-info/AUTHORS.rst
apybiomart-0.5.3.dist-info/LICENSE
apybiomart-0.5.3.dist-info/METADATA
apybiomart-0.5.3.dist-info/WHEEL
apybiomart-0.5.3.dist-info/entry_points.txt
apybiomart-0.5.3.dist-info/top_level.txt
apybiomart-0.5.3.dist-info/RECORD
