Metadata-Version: 2.1
Name: apybiomart
Version: 0.5.3
Summary: Async pythonic interface to Biomart.
Home-page: https://github.com/robertopreste/apybiomart
Author: Roberto Preste
Author-email: robertopreste@gmail.com
License: MIT license
Keywords: apybiomart
Platform: UNKNOWN
Classifier: Development Status :: 4 - Beta
Classifier: Intended Audience :: Developers
Classifier: License :: OSI Approved :: MIT License
Classifier: Natural Language :: English
Classifier: Topic :: Scientific/Engineering :: Bio-Informatics
Classifier: Programming Language :: Python :: 3
Classifier: Programming Language :: Python :: 3.5
Classifier: Programming Language :: Python :: 3.6
Classifier: Programming Language :: Python :: 3.7
Requires-Dist: requests
Requires-Dist: asyncio
Requires-Dist: aiohttp
Requires-Dist: pandas
